JDK Version Corretto 11.0.18
Compiled from "InvokeReflectCostTest.java"
public class com.tuya.pixiu.starter.InvokeReflectCostTest {
  public com.tuya.pixiu.starter.InvokeReflectCostTest();
    Code:
       0: aload_0
       1: invokespecial #1                  // Method java/lang/Object."<init>":()V
       4: return

  public void initMethod() throws java.lang.Throwable;
    Code:
       0: invokestatic  #2                  // Method java/lang/invoke/MethodHandles.lookup:()Ljava/lang/invoke/MethodHandles$Lookup;
       3: astore_1
       4: invokestatic  #3                  // Method java/lang/invoke/MethodHandles.publicLookup:()Ljava/lang/invoke/MethodHandles$Lookup;
       7: astore_2
       8: ldc           #4                  // class java/lang/String
      10: invokestatic  #5                  // Method java/lang/invoke/MethodType.methodType:(Ljava/lang/Class;)Ljava/lang/invoke/MethodType;
      13: astore_3
      14: aload_0
      15: ldc           #6                  // class com/tuya/pixiu/starter/TestPerson
      17: ldc           #7                  // String getName
      19: iconst_0
      20: anewarray     #8                  // class java/lang/Class
      23: invokevirtual #9                  // Method java/lang/Class.getDeclaredMethod:(Ljava/lang/String;[Ljava/lang/Class;)Ljava/lang/reflect/Method;
      26: putfield      #10                 // Field publicGetMethod:Ljava/lang/reflect/Method;
      29: aload_0
      30: ldc           #6                  // class com/tuya/pixiu/starter/TestPerson
      32: ldc           #11                 // String privateGetMobile
      34: iconst_0
      35: anewarray     #8                  // class java/lang/Class
      38: invokevirtual #9                  // Method java/lang/Class.getDeclaredMethod:(Ljava/lang/String;[Ljava/lang/Class;)Ljava/lang/reflect/Method;
      41: putfield      #12                 // Field privateAccessiableGetMethod:Ljava/lang/reflect/Method;
      44: aload_0
      45: getfield      #12                 // Field privateAccessiableGetMethod:Ljava/lang/reflect/Method;
      48: iconst_1
      49: invokevirtual #13                 // Method java/lang/reflect/Method.setAccessible:(Z)V
      52: aload_0
      53: aload_2
      54: aload_0
      55: getfield      #10                 // Field publicGetMethod:Ljava/lang/reflect/Method;
      58: invokevirtual #14                 // Method java/lang/invoke/MethodHandles$Lookup.unreflect:(Ljava/lang/reflect/Method;)Ljava/lang/invoke/MethodHandle;
      61: putfield      #15                 // Field publicMethodHandleOfPublicLookUp:Ljava/lang/invoke/MethodHandle;
      64: aload_0
      65: aload_1
      66: ldc           #6                  // class com/tuya/pixiu/starter/TestPerson
      68: ldc           #16                 // String getMobile
      70: aload_3
      71: invokevirtual #17                 // Method java/lang/invoke/MethodHandles$Lookup.findVirtual:(Ljava/lang/Class;Ljava/lang/String;Ljava/lang/invoke/MethodType;)Ljava/lang/invoke/MethodHandle;
      74: putfield      #18                 // Field protectMethodHandle:Ljava/lang/invoke/MethodHandle;
      77: aload_0
      78: aload_1
      79: aload_0
      80: getfield      #12                 // Field privateAccessiableGetMethod:Ljava/lang/reflect/Method;
      83: invokevirtual #14                 // Method java/lang/invoke/MethodHandles$Lookup.unreflect:(Ljava/lang/reflect/Method;)Ljava/lang/invoke/MethodHandle;
      86: putfield      #19                 // Field privateAccessiableGetMethodHandle:Ljava/lang/invoke/MethodHandle;
      89: aload_1
      90: ldc           #20                 // String apply
      92: ldc           #21                 // class java/util/function/Function
      94: invokestatic  #5                  // Method java/lang/invoke/MethodType.methodType:(Ljava/lang/Class;)Ljava/lang/invoke/MethodType;
      97: ldc           #22                 // class java/lang/Object
      99: ldc           #22                 // class java/lang/Object
     101: invokestatic  #23                 // Method java/lang/invoke/MethodType.methodType:(Ljava/lang/Class;Ljava/lang/Class;)Ljava/lang/invoke/MethodType;
     104: aload_1
     105: ldc           #6                  // class com/tuya/pixiu/starter/TestPerson
     107: ldc           #7                  // String getName
     109: ldc           #4                  // class java/lang/String
     111: invokestatic  #5                  // Method java/lang/invoke/MethodType.methodType:(Ljava/lang/Class;)Ljava/lang/invoke/MethodType;
     114: invokevirtual #17                 // Method java/lang/invoke/MethodHandles$Lookup.findVirtual:(Ljava/lang/Class;Ljava/lang/String;Ljava/lang/invoke/MethodType;)Ljava/lang/invoke/MethodHandle;
     117: ldc           #4                  // class java/lang/String
     119: ldc           #6                  // class com/tuya/pixiu/starter/TestPerson
     121: invokestatic  #23                 // Method java/lang/invoke/MethodType.methodType:(Ljava/lang/Class;Ljava/lang/Class;)Ljava/lang/invoke/MethodType;
     124: invokestatic  #24                 // Method java/lang/invoke/LambdaMetafactory.metafactory:(Ljava/lang/invoke/MethodHandles$Lookup;Ljava/lang/String;Ljava/lang/invoke/MethodType;Ljava/lang/invoke/MethodType;Ljava/lang/invoke/MethodHandle;Ljava/lang/invoke/MethodType;)Ljava/lang/invoke/CallSite;
     127: astore        4
     129: aload_0
     130: aload         4
     132: invokevirtual #25                 // Method java/lang/invoke/CallSite.getTarget:()Ljava/lang/invoke/MethodHandle;
     135: invokevirtual #26                 // Method java/lang/invoke/MethodHandle.invokeExact:()Ljava/util/function/Function;
     138: putfield      #27                 // Field getterFunction:Ljava/util/function/Function;
     141: goto          151
     144: astore        4
     146: aload         4
     148: invokevirtual #29                 // Method java/lang/Throwable.printStackTrace:()V
     151: return
    Exception table:
       from    to  target type
          14   141   144   Class java/lang/Throwable

  public void direct(org.openjdk.jmh.infra.Blackhole) throws java.lang.Throwable;
    Code:
       0: aload_1
       1: getstatic     #30                 // Field person:Lcom/tuya/pixiu/starter/TestPerson;
       4: getfield      #31                 // Field com/tuya/pixiu/starter/TestPerson.name:Ljava/lang/String;
       7: invokevirtual #32                 // Method org/openjdk/jmh/infra/Blackhole.consume:(Ljava/lang/Object;)V
      10: return

  public void directGetter(org.openjdk.jmh.infra.Blackhole) throws java.lang.Throwable;
    Code:
       0: aload_1
       1: getstatic     #30                 // Field person:Lcom/tuya/pixiu/starter/TestPerson;
       4: invokevirtual #33                 // Method com/tuya/pixiu/starter/TestPerson.getName:()Ljava/lang/String;
       7: invokevirtual #32                 // Method org/openjdk/jmh/infra/Blackhole.consume:(Ljava/lang/Object;)V
      10: return

  public void reflectGetter(org.openjdk.jmh.infra.Blackhole) throws java.lang.Throwable;
    Code:
       0: aload_0
       1: getfield      #10                 // Field publicGetMethod:Ljava/lang/reflect/Method;
       4: getstatic     #30                 // Field person:Lcom/tuya/pixiu/starter/TestPerson;
       7: iconst_0
       8: anewarray     #22                 // class java/lang/Object
      11: invokevirtual #34                 // Method java/lang/reflect/Method.invoke:(Ljava/lang/Object;[Ljava/lang/Object;)Ljava/lang/Object;
      14: checkcast     #4                  // class java/lang/String
      17: astore_2
      18: aload_1
      19: aload_2
      20: invokevirtual #32                 // Method org/openjdk/jmh/infra/Blackhole.consume:(Ljava/lang/Object;)V
      23: return

  public void reflectGetterAccessible(org.openjdk.jmh.infra.Blackhole) throws java.lang.Throwable;
    Code:
       0: aload_0
       1: getfield      #12                 // Field privateAccessiableGetMethod:Ljava/lang/reflect/Method;
       4: getstatic     #30                 // Field person:Lcom/tuya/pixiu/starter/TestPerson;
       7: iconst_0
       8: anewarray     #22                 // class java/lang/Object
      11: invokevirtual #34                 // Method java/lang/reflect/Method.invoke:(Ljava/lang/Object;[Ljava/lang/Object;)Ljava/lang/Object;
      14: checkcast     #4                  // class java/lang/String
      17: astore_2
      18: aload_1
      19: aload_2
      20: invokevirtual #32                 // Method org/openjdk/jmh/infra/Blackhole.consume:(Ljava/lang/Object;)V
      23: return

  public void publicLookUp(org.openjdk.jmh.infra.Blackhole) throws java.lang.Throwable;
    Code:
       0: aload_0
       1: getfield      #15                 // Field publicMethodHandleOfPublicLookUp:Ljava/lang/invoke/MethodHandle;
       4: getstatic     #30                 // Field person:Lcom/tuya/pixiu/starter/TestPerson;
       7: invokevirtual #35                 // Method java/lang/invoke/MethodHandle.invoke:(Lcom/tuya/pixiu/starter/TestPerson;)Ljava/lang/String;
      10: astore_2
      11: aload_1
      12: aload_2
      13: invokevirtual #32                 // Method org/openjdk/jmh/infra/Blackhole.consume:(Ljava/lang/Object;)V
      16: return

  public void lookUp(org.openjdk.jmh.infra.Blackhole) throws java.lang.Throwable;
    Code:
       0: aload_0
       1: getfield      #18                 // Field protectMethodHandle:Ljava/lang/invoke/MethodHandle;
       4: getstatic     #30                 // Field person:Lcom/tuya/pixiu/starter/TestPerson;
       7: invokevirtual #35                 // Method java/lang/invoke/MethodHandle.invoke:(Lcom/tuya/pixiu/starter/TestPerson;)Ljava/lang/String;
      10: astore_2
      11: aload_1
      12: aload_2
      13: invokevirtual #32                 // Method org/openjdk/jmh/infra/Blackhole.consume:(Ljava/lang/Object;)V
      16: return

  public void lookUpAccessible(org.openjdk.jmh.infra.Blackhole) throws java.lang.Throwable;
    Code:
       0: aload_0
       1: getfield      #19                 // Field privateAccessiableGetMethodHandle:Ljava/lang/invoke/MethodHandle;
       4: getstatic     #30                 // Field person:Lcom/tuya/pixiu/starter/TestPerson;
       7: invokevirtual #35                 // Method java/lang/invoke/MethodHandle.invoke:(Lcom/tuya/pixiu/starter/TestPerson;)Ljava/lang/String;
      10: astore_2
      11: aload_1
      12: aload_2
      13: invokevirtual #32                 // Method org/openjdk/jmh/infra/Blackhole.consume:(Ljava/lang/Object;)V
      16: return

  public void staticLookUp(org.openjdk.jmh.infra.Blackhole) throws java.lang.Throwable;
    Code:
       0: getstatic     #36                 // Field staticPublicMethodHandle:Ljava/lang/invoke/MethodHandle;
       3: getstatic     #30                 // Field person:Lcom/tuya/pixiu/starter/TestPerson;
       6: invokevirtual #35                 // Method java/lang/invoke/MethodHandle.invoke:(Lcom/tuya/pixiu/starter/TestPerson;)Ljava/lang/String;
       9: astore_2
      10: aload_1
      11: aload_2
      12: invokevirtual #32                 // Method org/openjdk/jmh/infra/Blackhole.consume:(Ljava/lang/Object;)V
      15: return

  public void lambdaMetaFactoryLookUp(org.openjdk.jmh.infra.Blackhole) throws java.lang.Throwable;
    Code:
       0: aload_0
       1: getfield      #27                 // Field getterFunction:Ljava/util/function/Function;
       4: getstatic     #30                 // Field person:Lcom/tuya/pixiu/starter/TestPerson;
       7: invokeinterface #37,  2           // InterfaceMethod java/util/function/Function.apply:(Ljava/lang/Object;)Ljava/lang/Object;
      12: checkcast     #4                  // class java/lang/String
      15: astore_2
      16: aload_1
      17: aload_2
      18: invokevirtual #32                 // Method org/openjdk/jmh/infra/Blackhole.consume:(Ljava/lang/Object;)V
      21: return

  static {};
    Code:
       0: invokestatic  #2                  // Method java/lang/invoke/MethodHandles.lookup:()Ljava/lang/invoke/MethodHandles$Lookup;
       3: astore_0
       4: ldc           #6                  // class com/tuya/pixiu/starter/TestPerson
       6: ldc           #7                  // String getName
       8: iconst_0
       9: anewarray     #8                  // class java/lang/Class
      12: invokevirtual #9                  // Method java/lang/Class.getDeclaredMethod:(Ljava/lang/String;[Ljava/lang/Class;)Ljava/lang/reflect/Method;
      15: astore_1
      16: aload_0
      17: aload_1
      18: invokevirtual #14                 // Method java/lang/invoke/MethodHandles$Lookup.unreflect:(Ljava/lang/reflect/Method;)Ljava/lang/invoke/MethodHandle;
      21: putstatic     #36                 // Field staticPublicMethodHandle:Ljava/lang/invoke/MethodHandle;
      24: goto          37
      27: astore_0
      28: new           #39                 // class java/lang/RuntimeException
      31: dup
      32: aload_0
      33: invokespecial #40                 // Method java/lang/RuntimeException."<init>":(Ljava/lang/Throwable;)V
      36: athrow
      37: new           #6                  // class com/tuya/pixiu/starter/TestPerson
      40: dup
      41: ldc           #41                 // String zhang
      43: ldc           #42                 // String 12345678
      45: invokespecial #43                 // Method com/tuya/pixiu/starter/TestPerson."<init>":(Ljava/lang/String;Ljava/lang/String;)V
      48: putstatic     #30                 // Field person:Lcom/tuya/pixiu/starter/TestPerson;
      51: return
    Exception table:
       from    to  target type
           0    24    27   Class java/lang/Exception
}
zhangzhipeideMacBook-Pro:starter zhangzhipei$

