public class com.walklown.learn.jarkata.base.NestClass$InnerClass {

  // 内部包含一个 final 的父对象引用
  final com.walklown.learn.jarkata.base.NestClass this$0;

  public com.walklown.learn.jarkata.base.NestClass$InnerClass(com.walklown.learn.jarkata.base.NestClass, java.lang.String);
    Code:
       0: aload_0
       1: aload_1
       2: putfield      #1                  // Field this$0:Lcom/walklown/learn/jarkata/base/NestClass;
       5: aload_0
       6: invokespecial #7                  // Method java/lang/Object."<init>":()V
       9: aload_0
      10: aload_2
      11: putfield      #13                 // Field aa:Ljava/lang/String;
      14: return

  public java.lang.String getA();
    Code:
       0: aload_0
       1: getfield      #1                  // Field this$0:Lcom/walklown/learn/jarkata/base/NestClass;
       4: getfield      #17                 // Field com/walklown/learn/jarkata/base/NestClass.a:Ljava/lang/String;
       7: areturn

  public com.walklown.learn.jarkata.base.NestClass getNestClassDemo();
    Code:
       0: aload_0
       1: getfield      #1                  // Field this$0:Lcom/walklown/learn/jarkata/base/NestClass;
       4: areturn
}
