Compiled from "NestClass.java"
public class com.walklown.learn.jarkata.base.NestClass {
  public com.walklown.learn.jarkata.base.NestClass();
    Code:
       0: aload_0
       1: invokespecial #1                  // Method java/lang/Object."<init>":()V
       4: aload_0
       5: new           #7                  // class com/walklown/learn/jarkata/base/NestClass$InnerClass
       8: dup
       9: aload_0
      10: ldc           #9                  // String aa
      12: invokespecial #11                 // Method com/walklown/learn/jarkata/base/NestClass$InnerClass."<init>":(Lcom/walklown/learn/jarkata/base/NestClass;Ljava/lang/String;)V
      15: putfield      #14                 // Field innerClass:Lcom/walklown/learn/jarkata/base/NestClass$InnerClass;
      18: return

  public java.lang.String getAa();
    Code:
       0: aload_0
       1: getfield      #14                 // Field innerClass:Lcom/walklown/learn/jarkata/base/NestClass$InnerClass;
       4: getfield      #20                 // Field com/walklown/learn/jarkata/base/NestClass$InnerClass.aa:Ljava/lang/String;
       7: areturn

  public com.walklown.learn.jarkata.base.NestClass$InnerClass getInnerClass();
    Code:
       0: aload_0
       1: getfield      #14                 // Field innerClass:Lcom/walklown/learn/jarkata/base/NestClass$InnerClass;
       4: areturn
}
