Compiled from "InvokeReflectDemo.java"
public class com.walklown.learn.jarkata.base.reflect.InvokeReflectDemo {
  public java.util.function.Function getterFunction;

  public com.walklown.learn.jarkata.base.reflect.InvokeReflectDemo();
    Code:
       0: aload_0
       1: invokespecial #1                  // Method java/lang/Object."<init>":()V
       4: invokestatic  #7                  // Method java/lang/invoke/MethodHandles.lookup:()Ljava/lang/invoke/MethodHandles$Lookup;
       7: astore_1
       8: aload_1
       9: ldc           #13                 // String apply
      11: ldc           #15                 // class java/util/function/Function
      13: invokestatic  #17                 // Method java/lang/invoke/MethodType.methodType:(Ljava/lang/Class;)Ljava/lang/invoke/MethodType;
      16: ldc           #2                  // class java/lang/Object
      18: ldc           #2                  // class java/lang/Object
      20: invokestatic  #23                 // Method java/lang/invoke/MethodType.methodType:(Ljava/lang/Class;Ljava/lang/Class;)Ljava/lang/invoke/MethodType;
      23: aload_1
      24: ldc           #26                 // class com/walklown/learn/jarkata/base/reflect/Person
      26: ldc           #28                 // String getName
      28: ldc           #30                 // class java/lang/String
      30: invokestatic  #17                 // Method java/lang/invoke/MethodType.methodType:(Ljava/lang/Class;)Ljava/lang/invoke/MethodType;
      33: invokevirtual #32                 // Method java/lang/invoke/MethodHandles$Lookup.findVirtual:(Ljava/lang/Class;Ljava/lang/String;Ljava/lang/invoke/MethodType;)Ljava/lang/invoke/MethodHandle;
      36: ldc           #30                 // class java/lang/String
      38: ldc           #26                 // class com/walklown/learn/jarkata/base/reflect/Person
      40: invokestatic  #23                 // Method java/lang/invoke/MethodType.methodType:(Ljava/lang/Class;Ljava/lang/Class;)Ljava/lang/invoke/MethodType;
      43: invokestatic  #38                 // Method java/lang/invoke/LambdaMetafactory.metafactory:(Ljava/lang/invoke/MethodHandles$Lookup;Ljava/lang/String;Ljava/lang/invoke/MethodType;Ljava/lang/invoke/MethodType;Ljava/lang/invoke/MethodHandle;Ljava/lang/invoke/MethodType;)Ljava/lang/invoke/CallSite;
      46: astore_2
      47: aload_0
      48: aload_2
      49: invokevirtual #44                 // Method java/lang/invoke/CallSite.getTarget:()Ljava/lang/invoke/MethodHandle;
      52: invokevirtual #50                 // Method java/lang/invoke/MethodHandle.invokeExact:()Ljava/util/function/Function;
      55: putfield      #56                 // Field getterFunction:Ljava/util/function/Function;
      58: goto          66
      61: astore_2
      62: aload_2
      63: invokevirtual #64                 // Method java/lang/Throwable.printStackTrace:()V
      66: return
    Exception table:
       from    to  target type
           8    58    61   Class java/lang/Throwable

  public static void main(java.lang.String[]);
    Code:
       0: new           #57                 // class com/walklown/learn/jarkata/base/reflect/InvokeReflectDemo
       3: dup
       4: invokespecial #67                 // Method "<init>":()V
       7: astore_1
       8: aload_1
       9: getfield      #56                 // Field getterFunction:Ljava/util/function/Function;
      12: getstatic     #68                 // Field person:Lcom/walklown/learn/jarkata/base/reflect/Person;
      15: invokeinterface #72,  2           // InterfaceMethod java/util/function/Function.apply:(Ljava/lang/Object;)Ljava/lang/Object;
      20: checkcast     #30                 // class java/lang/String
      23: astore_2
    Code:
       0: new           #26                 // class com/walklown/learn/jarkata/base/reflect/Person
       3: dup
       4: ldc           #75                 // String zhang
       6: ldc           #77                 // String 12345678
       8: invokespecial #79                 // Method com/walklown/learn/jarkata/base/reflect/Person."<init>":(Ljava/lang/String;Ljava/lang/String;)V
      11: putstatic     #68                 // Field person:Lcom/walklown/learn/jarkata/base/reflect/Person;
      14: return
}
